xem_wrapper/__init__.py
xem_wrapper/constants.py
xem_wrapper/exceptions.py
xem_wrapper/front_panel.py
xem_wrapper/main.py
xem_wrapper/ok.py
xem_wrapper/ok_wrapper.py
xem_wrapper/_linux/_ok.so
xem_wrapper/_linux/libokFrontPanel.so
xem_wrapper/_mac/_ok.so
xem_wrapper/_mac/libokFrontPanel.dylib
xem_wrapper/_windows/_ok.pyd
xem_wrapper/_windows/okFrontPanel.dll
xem_wrapper/_windows/okFrontPanel.lib
xem_wrapper-0.3.0.dist-info/LICENSE
xem_wrapper-0.3.0.dist-info/METADATA
xem_wrapper-0.3.0.dist-info/WHEEL
xem_wrapper-0.3.0.dist-info/top_level.txt
xem_wrapper-0.3.0.dist-info/RECORD
