Metadata-Version: 2.1
Name: xem-wrapper
Version: 0.3.0
Summary: Functions for interacting with a XEM device
Home-page: https://github.com/CuriBio/xem-wrapper
Author: Curi Bio
Author-email: contact@curibio.com
License: MIT
Platform: UNKNOWN
Classifier: Development Status :: 1 - Planning
Classifier: Intended Audience :: Science/Research
Classifier: License :: OSI Approved :: MIT License
Classifier: Programming Language :: Python
Classifier: Programming Language :: Python :: 3
Classifier: Programming Language :: Python :: 3.8
Classifier: Programming Language :: Python :: 3.9
Classifier: Topic :: Scientific/Engineering
License-File: LICENSE
Requires-Dist: stdlib-utils (>=0.5.2)
